deps/Base38.py
deps/__init__.py
deps/generate_setup_payload.py
deps/mfg_gen.py
deps/spake2p.py
deps/patches/0001-mfg-gen-no-bin-and-replace-print-by-logging.patch
sources/__init__.py
sources/cert_utils.py
sources/chip_nvs.py
sources/matter_secure_cert.py
sources/mfg_tool.py
sources/utils.py
tests/__init__.py
tests/test_integration.py
tests/utils.py
esp_matter_mfg_tool-1.0.21.dist-info/METADATA
esp_matter_mfg_tool-1.0.21.dist-info/WHEEL
esp_matter_mfg_tool-1.0.21.dist-info/entry_points.txt
esp_matter_mfg_tool-1.0.21.dist-info/top_level.txt
esp_matter_mfg_tool-1.0.21.dist-info/RECORD
